zzzzztest/__init__.py
zzzzztest/tools/__init__.py
zzzzztest/tools/get_resume_parse.py
zzzzztest-0.0.7.dist-info/METADATA
zzzzztest-0.0.7.dist-info/WHEEL
zzzzztest-0.0.7.dist-info/top_level.txt
zzzzztest-0.0.7.dist-info/RECORD
