Metadata-Version: 2.4
Name: zzzzztest
Version: 0.0.7
Summary: zzzzztest
Home-page: https://github.com/123123123123/zzzzztest
Author: admin
Author-email: admin@qq.com  
Dynamic: author
Dynamic: author-email
Dynamic: home-page
Dynamic: summary
